{
  "main": {
    "id": "baac5fe5b62e79fc",
    "type": "split",
    "children": [
      {
        "id": "ca93554d946f503f",
        "type": "tabs",
        "children": [
          {
            "id": "b43a9cd2b3808950",
            "type": "leaf",
            "state": {
              "type": "empty",
              "state": {}
            }
          },
          {
            "id": "02316791dbbdc90b",
            "type": "leaf",
            "state": {
              "type": "markdown",
              "state": {
                "file": "Initial Ideas.md",
                "mode": "source",
                "source": false
              }
            }
          },
          {
            "id": "8b678f3ca46f3b6c",
            "type": "leaf",
            "state": {
              "type": "markdown",
              "state": {
                "file": "Initial Ideas.md",
                "mode": "source",
                "source": false
              }
            }
          }
        ],
        "currentTab": 2
      }
    ],
    "direction": "vertical"
  },
  "left": {
    "id": "46013c5a2cb97a67",
    "type": "split",
    "children": [
      {
        "id": "6c42eb9bb62e850a",
        "type": "tabs",
        "children": [
          {
            "id": "71400ea595d99752",
            "type": "leaf",
            "state": {
              "type": "file-explorer",
              "state": {
                "sortOrder": "alphabetical"
              }
            }
          },
          {
            "id": "85ee3c938968b04a",
            "type": "leaf",
            "state": {
              "type": "search",
              "state": {
                "query": "",
                "matchingCase": false,
                "explainSearch": false,
                "collapseAll": false,
                "extraContext": false,
                "sortOrder": "alphabetical"
              }
            }
          },
          {
            "id": "0b264a40e29633bc",
            "type": "leaf",
            "state": {
              "type": "bookmarks",
              "state": {}
            }
          }
        ]
      }
    ],
    "direction": "horizontal",
    "width": 300
  },
  "right": {
    "id": "cf519ee7fb937d92",
    "type": "split",
    "children": [
      {
        "id": "0d492379ad6a208a",
        "type": "tabs",
        "children": [
          {
            "id": "cc1b9f8fb0abe605",
            "type": "leaf",
            "state": {
              "type": "backlink",
              "state": {
                "file": "Initial Ideas.md",
                "collapseAll": false,
                "extraContext": false,
                "sortOrder": "alphabetical",
                "showSearch": false,
                "searchQuery": "",
                "backlinkCollapsed": false,
                "unlinkedCollapsed": true
              }
            }
          },
          {
            "id": "649fbae74a6dcdd6",
            "type": "leaf",
            "state": {
              "type": "outgoing-link",
              "state": {
                "file": "Initial Ideas.md",
                "linksCollapsed": false,
                "unlinkedCollapsed": true
              }
            }
          },
          {
            "id": "8b3ef2a20e3fbfb5",
            "type": "leaf",
            "state": {
              "type": "tag",
              "state": {
                "sortOrder": "frequency",
                "useHierarchy": true
              }
            }
          },
          {
            "id": "b1a27296920f25ec",
            "type": "leaf",
            "state": {
              "type": "outline",
              "state": {
                "file": "Initial Ideas.md"
              }
            }
          }
        ]
      }
    ],
    "direction": "horizontal",
    "width": 300,
    "collapsed": true
  },
  "left-ribbon": {
    "hiddenItems": {
      "switcher:Open quick switcher": false,
      "graph:Open graph view": false,
      "canvas:Create new canvas": false,
      "daily-notes:Open today's daily note": false,
      "templates:Insert template": false,
      "command-palette:Open command palette": false
    }
  },
  "active": "8b678f3ca46f3b6c",
  "lastOpenFiles": [
    "Images/Complex with notes.png",
    "Images/Simple.png",
    "Images/Complex.png",
    "Initial Ideas.md",
    "Magical Diagram Inspiration.md",
    "Untitled.md",
    "Images"
  ]
}